2023/2020B3A70785P.v
// BITS ID: 2020B3A70785P
// Name: Anish Ashish Kasegaonkar

module JK(q, qbar, j, k, CLK);
	output reg q, qbar;
	input j, k, CLK;
	
	// Initialised as such, so that the counter starts from 0 at the first clock edge
	// Using behavioural modelling
	initial begin
		q <= 1'b1;
		qbar <= 1'b0;
	end
	always @(negedge CLK) begin
		if(j == 0 && k == 0) begin
			q <= q;
			qbar <= qbar;
		end
		else if(j == 1 && k == 0) begin
			q <= 1'b1;
			qbar <= 1'b0;
		end
		else if(j == 0 && k == 1) begin
			q <= 1'b0;
			qbar <= 1'b1;
		end
		else begin
			q <= ~q;
			qbar <= ~qbar;
		end
	end
endmodule

module BCD_Counter(Q_out, CLK);
	output [3:0] Q_out;
	input CLK;
	
	wire [3:0] Q_bar;
	wire q1q2;
	
	// Using gate-level modelling
	and a0(q1q2, Q_out[1], Q_out[2]);
	JK j0(Q_out[0], Q_bar[0], 1'b1, 1'b1, CLK);
	JK j1(Q_out[1], Q_bar[1], Q_bar[3], 1'b1, Q_out[0]);
	JK j2(Q_out[2], Q_bar[2], 1'b1, 1'b1, Q_out[1]);
	JK j3(Q_out[3], Q_bar[3], q1q2, 1'b1, Q_out[0]);
endmodule

module MEM_16(D_16, A_4);
	output reg [15:0] D_16;
	input [3:0] A_4;
	
	// Using behavioural modelling
	always@(*) begin
		case(A_4)
			4'b0000: D_16 = 16'h0001;
			4'b0001: D_16 = 16'h0002;
			4'b0010: D_16 = 16'h0004;
			4'b0011: D_16 = 16'h0008;
			4'b0100: D_16 = 16'h0010;
			4'b0101: D_16 = 16'h0020;
			4'b0110: D_16 = 16'h0000;
			4'b0111: D_16 = 16'h0000;
			4'b1000: D_16 = 16'h0000;
			4'b1001: D_16 = 16'h0000;
			4'b1010: D_16 = 16'h0400;
			4'b1011: D_16 = 16'h0800;
			4'b1100: D_16 = 16'h1000;
			4'b1101: D_16 = 16'h0000;
			4'b1110: D_16 = 16'h0000;
			4'b1111: D_16 = 16'h0000;
		endcase
	end
endmodule

module MUX_16(O, I_16, S_4);
	output reg O;
	input [15:0] I_16;
	input [3:0] S_4;
	
	// assign O = I_16[S_4]; -> Can be used for simplicity, after assigning O as a wire instead of reg
	
	// Using behavioural modelling
	always @(*) begin
		case(S_4)
			4'b0000: O = I_16[0];
			4'b0001: O = I_16[1];
			4'b0010: O = I_16[2];
			4'b0011: O = I_16[3];
			4'b0100: O = I_16[4];
			4'b0101: O = I_16[5];
			4'b0110: O = I_16[6];
			4'b0111: O = I_16[7];
			4'b1000: O = I_16[8];
			4'b1001: O = I_16[9];
			4'b1010: O = I_16[10];
			4'b1011: O = I_16[11];
			4'b1100: O = I_16[12];
			4'b1101: O = I_16[13];
			4'b1110: O = I_16[14];
			4'b1111: O = I_16[15];
		endcase
	end
endmodule

module INTG(OUT, CLK);
	output OUT;
	input CLK;
	
	wire [3:0] Q_out;
	wire [15:0] D_16;
	
	BCD_Counter b(Q_out, CLK);
	MEM_16 m(D_16, Q_out);
	MUX_16 mx(OUT, D_16, Q_out);
endmodule

module TESTBENCH;
	reg CLK;
	wire OUT;
	
	INTG i(OUT, CLK);
	
	initial begin
		$dumpfile("t.vcd");
		$dumpvars;
	end
	
	initial begin
		CLK = 1'b1;
		repeat(1000)
			#1 CLK = ~CLK;
	end
	
	initial begin
		$monitor($time, " OUT = %b, CLK = %b", OUT, CLK);
		// The output is 1 for first 6 clock negedges (1->0 of clock), and is 0 for the next 4 clock edges
		#100 $finish;
	end
endmodule

2023/t.vcd
$date
	Mon Nov 20 20:20:58 2023
$end
$version
	Icarus Verilog
$end
$timescale
	1s
$end
$scope module TESTBENCH $end
$var wire 1 ! OUT $end
$var reg 1 " CLK $end
$scope module i $end
$var wire 1 " CLK $end
$var wire 4 # Q_out [3:0] $end
$var wire 1 ! OUT $end
$var wire 16 $ D_16 [15:0] $end
$scope module b $end
$var wire 1 " CLK $end
$var wire 1 % q1q2 $end
$var wire 4 & Q_out [3:0] $end
$var wire 4 ' Q_bar [3:0] $end
$scope module j0 $end
$var wire 1 " CLK $end
$var wire 1 ( j $end
$var wire 1 ) k $end
$var reg 1 * q $end
$var reg 1 + qbar $end
$upscope $end
$scope module j1 $end
$var wire 1 , CLK $end
$var wire 1 - j $end
$var wire 1 . k $end
$var reg 1 / q $end
$var reg 1 0 qbar $end
$upscope $end
$scope module j2 $end
$var wire 1 1 CLK $end
$var wire 1 2 j $end
$var wire 1 3 k $end
$var reg 1 4 q $end
$var reg 1 5 qbar $end
$upscope $end
$scope module j3 $end
$var wire 1 6 CLK $end
$var wire 1 % j $end
$var wire 1 7 k $end
$var reg 1 8 q $end
$var reg 1 9 qbar $end
$upscope $end
$upscope $end
$scope module m $end
$var wire 4 : A_4 [3:0] $end
$var reg 16 ; D_16 [15:0] $end
$upscope $end
$scope module mx $end
$var wire 16 < I_16 [15:0] $end
$var wire 4 = S_4 [3:0] $end
$var reg 1 ! O $end
$upscope $end
$upscope $end
$upscope $end
$enddefinitions $end
$comment Show the parameter values. $end
$dumpall
$end
#0
$dumpvars
b1111 =
b0 <
b0 ;
b1111 :
09
18
17
16
05
14
13
12
11
00
1/
1.
0-
1,
0+
1*
1)
1(
b0 '
b1111 &
1%
b0 $
b1111 #
1"
0!
$end
#1
15
04
0%
1!
1-
01
b1 $
b1 ;
b1 <
19
08
10
0/
06
0,
b1111 '
1+
b0 #
b0 &
b0 :
b0 =
0*
0"
#2
1"
#3
16
1,
b10 $
b10 ;
b10 <
1!
b1110 '
0+
b1 #
b1 &
b1 :
b1 =
1*
0"
#4
1"
#5
11
00
1/
06
0,
b100 $
b100 ;
b100 <
1!
b1101 '
1+
b10 #
b10 &
b10 :
b10 =
0*
0"
#6
1"
#7
16
1,
b1000 $
b1000 ;
b1000 <
1!
b1100 '
0+
b11 #
b11 &
b11 :
b11 =
1*
0"
#8
1"
#9
05
14
01
10
0/
06
0,
b10000 $
b10000 ;
b10000 <
1!
b1011 '
1+
b100 #
b100 &
b100 :
b100 =
0*
0"
#10
1"
#11
16
1,
b100000 $
b100000 ;
b100000 <
1!
b1010 '
0+
b101 #
b101 &
b101 :
b101 =
1*
0"
#12
1"
#13
1%
11
00
1/
06
0,
b0 $
b0 ;
b0 <
0!
b1001 '
1+
b110 #
b110 &
b110 :
b110 =
0*
0"
#14
1"
#15
16
1,
b1000 '
0+
b111 #
b111 &
b111 :
b111 =
1*
0"
#16
1"
#17
15
04
0%
0!
0-
01
b0 $
b0 ;
b0 <
09
18
10
0/
06
0,
b111 '
1+
b1000 #
b1000 &
b1000 :
b1000 =
0*
0"
#18
1"
#19
16
1,
b110 '
0+
b1001 #
b1001 &
b1001 :
b1001 =
1*
0"
#20
1"
#21
1!
1-
b1 $
b1 ;
b1 <
19
08
06
0,
b1111 '
1+
b0 #
b0 &
b0 :
b0 =
0*
0"
#22
1"
#23
16
1,
b10 $
b10 ;
b10 <
1!
b1110 '
0+
b1 #
b1 &
b1 :
b1 =
1*
0"
#24
1"
#25
11
00
1/
06
0,
b100 $
b100 ;
b100 <
1!
b1101 '
1+
b10 #
b10 &
b10 :
b10 =
0*
0"
#26
1"
#27
16
1,
b1000 $
b1000 ;
b1000 <
1!
b1100 '
0+
b11 #
b11 &
b11 :
b11 =
1*
0"
#28
1"
#29
05
14
01
10
0/
06
0,
b10000 $
b10000 ;
b10000 <
1!
b1011 '
1+
b100 #
b100 &
b100 :
b100 =
0*
0"
#30
1"
#31
16
1,
b100000 $
b100000 ;
b100000 <
1!
b1010 '
0+
b101 #
b101 &
b101 :
b101 =
1*
0"
#32
1"
#33
1%
11
00
1/
06
0,
b0 $
b0 ;
b0 <
0!
b1001 '
1+
b110 #
b110 &
b110 :
b110 =
0*
0"
#34
1"
#35
16
1,
b1000 '
0+
b111 #
b111 &
b111 :
b111 =
1*
0"
#36
1"
#37
15
04
0%
0!
0-
01
b0 $
b0 ;
b0 <
09
18
10
0/
06
0,
b111 '
1+
b1000 #
b1000 &
b1000 :
b1000 =
0*
0"
#38
1"
#39
16
1,
b110 '
0+
b1001 #
b1001 &
b1001 :
b1001 =
1*
0"
#40
1"
#41
1!
1-
b1 $
b1 ;
b1 <
19
08
06
0,
b1111 '
1+
b0 #
b0 &
b0 :
b0 =
0*
0"
#42
1"
#43
16
1,
b10 $
b10 ;
b10 <
1!
b1110 '
0+
b1 #
b1 &
b1 :
b1 =
1*
0"
#44
1"
#45
11
00
1/
06
0,
b100 $
b100 ;
b100 <
1!
b1101 '
1+
b10 #
b10 &
b10 :
b10 =
0*
0"
#46
1"
#47
16
1,
b1000 $
b1000 ;
b1000 <
1!
b1100 '
0+
b11 #
b11 &
b11 :
b11 =
1*
0"
#48
1"
#49
05
14
01
10
0/
06
0,
b10000 $
b10000 ;
b10000 <
1!
b1011 '
1+
b100 #
b100 &
b100 :
b100 =
0*
0"
#50
1"
#51
16
1,
b100000 $
b100000 ;
b100000 <
1!
b1010 '
0+
b101 #
b101 &
b101 :
b101 =
1*
0"
#52
1"
#53
1%
11
00
1/
06
0,
b0 $
b0 ;
b0 <
0!
b1001 '
1+
b110 #
b110 &
b110 :
b110 =
0*
0"
#54
1"
#55
16
1,
b1000 '
0+
b111 #
b111 &
b111 :
b111 =
1*
0"
#56
1"
#57
15
04
0%
0!
0-
01
b0 $
b0 ;
b0 <
09
18
10
0/
06
0,
b111 '
1+
b1000 #
b1000 &
b1000 :
b1000 =
0*
0"
#58
1"
#59
16
1,
b110 '
0+
b1001 #
b1001 &
b1001 :
b1001 =
1*
0"
#60
1"
#61
1!
1-
b1 $
b1 ;
b1 <
19
08
06
0,
b1111 '
1+
b0 #
b0 &
b0 :
b0 =
0*
0"
#62
1"
#63
16
1,
b10 $
b10 ;
b10 <
1!
b1110 '
0+
b1 #
b1 &
b1 :
b1 =
1*
0"
#64
1"
#65
11
00
1/
06
0,
b100 $
b100 ;
b100 <
1!
b1101 '
1+
b10 #
b10 &
b10 :
b10 =
0*
0"
#66
1"
#67
16
1,
b1000 $
b1000 ;
b1000 <
1!
b1100 '
0+
b11 #
b11 &
b11 :
b11 =
1*
0"
#68
1"
#69
05
14
01
10
0/
06
0,
b10000 $
b10000 ;
b10000 <
1!
b1011 '
1+
b100 #
b100 &
b100 :
b100 =
0*
0"
#70
1"
#71
16
1,
b100000 $
b100000 ;
b100000 <
1!
b1010 '
0+
b101 #
b101 &
b101 :
b101 =
1*
0"
#72
1"
#73
1%
11
00
1/
06
0,
b0 $
b0 ;
b0 <
0!
b1001 '
1+
b110 #
b110 &
b110 :
b110 =
0*
0"
#74
1"
#75
16
1,
b1000 '
0+
b111 #
b111 &
b111 :
b111 =
1*
0"
#76
1"
#77
15
04
0%
0!
0-
01
b0 $
b0 ;
b0 <
09
18
10
0/
06
0,
b111 '
1+
b1000 #
b1000 &
b1000 :
b1000 =
0*
0"
#78
1"
#79
16
1,
b110 '
0+
b1001 #
b1001 &
b1001 :
b1001 =
1*
0"
#80
1"
#81
1!
1-
b1 $
b1 ;
b1 <
19
08
06
0,
b1111 '
1+
b0 #
b0 &
b0 :
b0 =
0*
0"
#82
1"
#83
16
1,
b10 $
b10 ;
b10 <
1!
b1110 '
0+
b1 #
b1 &
b1 :
b1 =
1*
0"
#84
1"
#85
11
00
1/
06
0,
b100 $
b100 ;
b100 <
1!
b1101 '
1+
b10 #
b10 &
b10 :
b10 =
0*
0"
#86
1"
#87
16
1,
b1000 $
b1000 ;
b1000 <
1!
b1100 '
0+
b11 #
b11 &
b11 :
b11 =
1*
0"
#88
1"
#89
05
14
01
10
0/
06
0,
b10000 $
b10000 ;
b10000 <
1!
b1011 '
1+
b100 #
b100 &
b100 :
b100 =
0*
0"
#90
1"
#91
16
1,
b100000 $
b100000 ;
b100000 <
1!
b1010 '
0+
b101 #
b101 &
b101 :
b101 =
1*
0"
#92
1"
#93
1%
11
00
1/
06
0,
b0 $
b0 ;
b0 <
0!
b1001 '
1+
b110 #
b110 &
b110 :
b110 =
0*
0"
#94
1"
#95
16
1,
b1000 '
0+
b111 #
b111 &
b111 :
b111 =
1*
0"
#96
1"
#97
15
04
0%
0!
0-
01
b0 $
b0 ;
b0 <
09
18
10
0/
06
0,
b111 '
1+
b1000 #
b1000 &
b1000 :
b1000 =
0*
0"
#98
1"
#99
16
1,
b110 '
0+
b1001 #
b1001 &
b1001 :
b1001 =
1*
0"
