2017/2020B3A70785P.v
// 2020B3A70785P
module MUX_SMALL(out, in0, in1, sel);
    input in0, in1, sel;
    output out;
    assign out = (in0 & ~sel) | (in1 & sel);
endmodule

module MUX_BIG(out, in0, in1, in2, in3, in4, in5, in6, in7, sel);
    input in0, in1, in2, in3, in4, in5, in6, in7;
    input [2:0] sel;
    output out;
    wire w0, w1, w2, w3, w4, w5;
    MUX_SMALL m0(w0, in0, in1, sel[0]);
    MUX_SMALL m1(w1, in2, in3, sel[0]);
    MUX_SMALL m2(w2, in4, in5, sel[0]);
    MUX_SMALL m3(w3, in6, in7, sel[0]);
    MUX_SMALL m4(w4, w0, w1, sel[1]);
    MUX_SMALL m5(w5, w2, w3, sel[1]);
    MUX_SMALL m6(out, w4, w5, sel[2]);
endmodule

module TFF(q, t, clk, clear);
    input t, clk, clear;
    output reg q;
    always @(negedge clear or posedge clk) begin
        if(!clear)
            q <= 1'b0;
        else if(t)
            q <= ~q;
        else
            q <= q;
    end
endmodule

module COUNTER_4BIT(q0, q1, q2, q3, clk, clear);
    input clk, clear;
    output q0, q1, q2, q3;  
    TFF t1(q0, 1'b1, clk, clear);
    TFF t2(q1, q0, clk, clear);
    TFF t3(q2, q0&q1, clk, clear);
    TFF t4(q3, q0&q1&q2, clk, clear);
endmodule

module COUNTER_3BIT(q0, q1, q2, clk, clear);
    input clk, clear;
    output q0, q1, q2;
    TFF t1(q0, 1'b1, clk, clear);
    TFF t2(q1, q0, clk, clear);
    TFF t3(q2, q0&q1, clk, clear);
endmodule

module MEMORY(o0, o1, o2, o3, o4, o5, o6, o7, i0, i1, i2, i3);
    input i0, i1, i2, i3;
    output reg o0, o1, o2, o3, o4, o5, o6, o7;
    reg [7:0] r0, r1, r2, r3, r4, r5, r6, r7, r8, r9, r10, r11, r12, r13, r14, r15;
    initial begin
        r0 = 8'hCC;
        r1 = 8'hAA;
        r2 = 8'hCC;
        r3 = 8'hAA;
        r4 = 8'hCC;
        r5 = 8'hAA;
        r6 = 8'hCC;
        r7 = 8'hAA;
        r8 = 8'hCC;
        r9 = 8'hAA;
        r10 = 8'hCC;
        r11 = 8'hAA;
        r12 = 8'hCC;
        r13 = 8'hAA;
        r14 = 8'hCC;
        r15 = 8'hAA;
    end
    always @(i0 or i1 or i2 or i3) begin
        case ({i3, i2, i1, i0})
            4'b0000: {o7, o6, o5, o4, o3, o2, o1, o0} = r0;
            4'b0001: {o7, o6, o5, o4, o3, o2, o1, o0} = r1;
            4'b0010: {o7, o6, o5, o4, o3, o2, o1, o0} = r2;
            4'b0011: {o7, o6, o5, o4, o3, o2, o1, o0} = r3;
            4'b0100: {o7, o6, o5, o4, o3, o2, o1, o0} = r4;
            4'b0101: {o7, o6, o5, o4, o3, o2, o1, o0} = r5;
            4'b0110: {o7, o6, o5, o4, o3, o2, o1, o0} = r6;
            4'b0111: {o7, o6, o5, o4, o3, o2, o1, o0} = r7;
            4'b1000: {o7, o6, o5, o4, o3, o2, o1, o0} = r8;
            4'b1001: {o7, o6, o5, o4, o3, o2, o1, o0} = r9;
            4'b1010: {o7, o6, o5, o4, o3, o2, o1, o0} = r10;
            4'b1011: {o7, o6, o5, o4, o3, o2, o1, o0} = r11;
            4'b1100: {o7, o6, o5, o4, o3, o2, o1, o0} = r12;
            4'b1101: {o7, o6, o5, o4, o3, o2, o1, o0} = r13;
            4'b1101: {o7, o6, o5, o4, o3, o2, o1, o0} = r14;
            4'b1111: {o7, o6, o5, o4, o3, o2, o1, o0} = r15;
        endcase
    end
endmodule

module INTG(waveform, clk, clear);
    input clk, clear;
    output waveform;
    wire q00, q01, q02, q10, q11, q12, q13;
    wire o0, o1, o2, o3, o4, o5, o6, o7;

    COUNTER_3BIT c1(q00, q01, q02, clk, clear);
    COUNTER_4BIT c2(q10, q11, q12, q13, q00&q01&q02, clear);
    MEMORY mem1(o0, o1, o2, o3, o4, o5, o6, o7, q10, q11, q12, q13);
    MUX_BIG mux1(waveform, o0, o1, o2, o3, o4, o5, o6, o7, {q02, q01, q00});
endmodule

module tb;
    reg clk = 0, clear;
    wire waveform;
    INTG i(waveform, clk, clear);
    always
        #1 clk = ~clk;
    initial begin
        $dumpfile("filename.vcd");
        $dumpvars;
    end
    initial begin
        clear = 0; clk = 0;
        $monitor($time, " waveform=%b, clk=%b, clear=%b\n", waveform, clk, clear);
        #1 clear = 1;
        #100 $finish;
    end
endmodule

2017/filename.vcd
$date
	Sat Nov 18 00:49:05 2023
$end
$version
	Icarus Verilog
$end
$timescale
	1s
$end
$scope module tb $end
$var wire 1 ! waveform $end
$var reg 1 " clear $end
$var reg 1 # clk $end
$scope module i $end
$var wire 1 " clear $end
$var wire 1 # clk $end
$var wire 1 ! waveform $end
$var wire 1 $ q13 $end
$var wire 1 % q12 $end
$var wire 1 & q11 $end
$var wire 1 ' q10 $end
$var wire 1 ( q02 $end
$var wire 1 ) q01 $end
$var wire 1 * q00 $end
$var wire 1 + o7 $end
$var wire 1 , o6 $end
$var wire 1 - o5 $end
$var wire 1 . o4 $end
$var wire 1 / o3 $end
$var wire 1 0 o2 $end
$var wire 1 1 o1 $end
$var wire 1 2 o0 $end
$scope module c1 $end
$var wire 1 " clear $end
$var wire 1 # clk $end
$var wire 1 ( q2 $end
$var wire 1 ) q1 $end
$var wire 1 * q0 $end
$scope module t1 $end
$var wire 1 " clear $end
$var wire 1 # clk $end
$var wire 1 3 t $end
$var reg 1 * q $end
$upscope $end
$scope module t2 $end
$var wire 1 " clear $end
$var wire 1 # clk $end
$var wire 1 * t $end
$var reg 1 ) q $end
$upscope $end
$scope module t3 $end
$var wire 1 " clear $end
$var wire 1 # clk $end
$var wire 1 4 t $end
$var reg 1 ( q $end
$upscope $end
$upscope $end
$scope module c2 $end
$var wire 1 " clear $end
$var wire 1 5 clk $end
$var wire 1 $ q3 $end
$var wire 1 % q2 $end
$var wire 1 & q1 $end
$var wire 1 ' q0 $end
$scope module t1 $end
$var wire 1 " clear $end
$var wire 1 5 clk $end
$var wire 1 6 t $end
$var reg 1 ' q $end
$upscope $end
$scope module t2 $end
$var wire 1 " clear $end
$var wire 1 5 clk $end
$var wire 1 ' t $end
$var reg 1 & q $end
$upscope $end
$scope module t3 $end
$var wire 1 " clear $end
$var wire 1 5 clk $end
$var wire 1 7 t $end
$var reg 1 % q $end
$upscope $end
$scope module t4 $end
$var wire 1 " clear $end
$var wire 1 5 clk $end
$var wire 1 8 t $end
$var reg 1 $ q $end
$upscope $end
$upscope $end
$scope module mem1 $end
$var wire 1 ' i0 $end
$var wire 1 & i1 $end
$var wire 1 % i2 $end
$var wire 1 $ i3 $end
$var reg 1 2 o0 $end
$var reg 1 1 o1 $end
$var reg 1 0 o2 $end
$var reg 1 / o3 $end
$var reg 1 . o4 $end
$var reg 1 - o5 $end
$var reg 1 , o6 $end
$var reg 1 + o7 $end
$var reg 8 9 r0 [7:0] $end
$var reg 8 : r1 [7:0] $end
$var reg 8 ; r10 [7:0] $end
$var reg 8 < r11 [7:0] $end
$var reg 8 = r12 [7:0] $end
$var reg 8 > r13 [7:0] $end
$var reg 8 ? r14 [7:0] $end
$var reg 8 @ r15 [7:0] $end
$var reg 8 A r2 [7:0] $end
$var reg 8 B r3 [7:0] $end
$var reg 8 C r4 [7:0] $end
$var reg 8 D r5 [7:0] $end
$var reg 8 E r6 [7:0] $end
$var reg 8 F r7 [7:0] $end
$var reg 8 G r8 [7:0] $end
$var reg 8 H r9 [7:0] $end
$upscope $end
$scope module mux1 $end
$var wire 1 2 in0 $end
$var wire 1 1 in1 $end
$var wire 1 0 in2 $end
$var wire 1 / in3 $end
$var wire 1 . in4 $end
$var wire 1 - in5 $end
$var wire 1 , in6 $end
$var wire 1 + in7 $end
$var wire 3 I sel [2:0] $end
$var wire 1 J w5 $end
$var wire 1 K w4 $end
$var wire 1 L w3 $end
$var wire 1 M w2 $end
$var wire 1 N w1 $end
$var wire 1 O w0 $end
$var wire 1 ! out $end
$scope module m0 $end
$var wire 1 2 in0 $end
$var wire 1 1 in1 $end
$var wire 1 O out $end
$var wire 1 P sel $end
$upscope $end
$scope module m1 $end
$var wire 1 0 in0 $end
$var wire 1 / in1 $end
$var wire 1 N out $end
$var wire 1 Q sel $end
$upscope $end
$scope module m2 $end
$var wire 1 . in0 $end
$var wire 1 - in1 $end
$var wire 1 M out $end
$var wire 1 R sel $end
$upscope $end
$scope module m3 $end
$var wire 1 , in0 $end
$var wire 1 + in1 $end
$var wire 1 L out $end
$var wire 1 S sel $end
$upscope $end
$scope module m4 $end
$var wire 1 O in0 $end
$var wire 1 N in1 $end
$var wire 1 K out $end
$var wire 1 T sel $end
$upscope $end
$scope module m5 $end
$var wire 1 M in0 $end
$var wire 1 L in1 $end
$var wire 1 J out $end
$var wire 1 U sel $end
$upscope $end
$scope module m6 $end
$var wire 1 K in0 $end
$var wire 1 J in1 $end
$var wire 1 ! out $end
$var wire 1 V sel $end
$upscope $end
$upscope $end
$upscope $end
$upscope $end
$enddefinitions $end
$comment Show the parameter values. $end
$dumpall
$end
#0
$dumpvars
0V
0U
0T
0S
0R
0Q
0P
0O
1N
0M
1L
0K
0J
b0 I
b10101010 H
b11001100 G
b10101010 F
b11001100 E
b10101010 D
b11001100 C
b10101010 B
b11001100 A
b10101010 @
b11001100 ?
b10101010 >
b11001100 =
b10101010 <
b11001100 ;
b10101010 :
b11001100 9
08
07
16
05
04
13
02
01
10
1/
0.
0-
1,
1+
0*
0)
0(
0'
0&
0%
0$
0#
0"
0!
$end
#1
1P
1Q
1R
1S
b1 I
1*
1"
1#
#2
0#
#3
1!
1N
1L
1K
1J
0P
0Q
0R
0S
1T
1U
0*
b10 I
1)
1#
#4
0#
#5
14
1P
1Q
1R
1S
b11 I
1*
1#
#6
0#
#7
0,
1-
00
11
1'
0!
0N
0L
0K
0J
0P
0Q
0R
0S
04
0T
0U
1V
05
0*
0)
b100 I
1(
1#
#8
0#
#9
1!
1K
1J
1O
1N
1M
1L
1P
1Q
1R
1S
b101 I
1*
1#
#10
0#
#11
0!
0K
0J
0O
0N
0M
0L
0P
0Q
0R
0S
1T
1U
0*
b110 I
1)
1#
#12
0#
#13
1,
0-
10
01
0'
1&
1!
1K
1J
0O
1N
0M
1L
15
14
1P
1Q
1R
1S
b111 I
1*
1#
#14
0#
#15
1N
1L
0K
0J
0!
0P
0Q
0R
0S
04
0T
0U
0V
05
0*
0)
b0 I
0(
1#
#16
0#
#17
1P
1Q
1R
1S
b1 I
1*
1#
#18
0#
#19
1!
1N
1L
1K
1J
0P
0Q
0R
0S
1T
1U
0*
b10 I
1)
1#
#20
0#
#21
14
1P
1Q
1R
1S
b11 I
1*
1#
#22
0#
#23
0,
1-
00
11
17
1'
0!
0N
0L
0K
0J
0P
0Q
0R
0S
04
0T
0U
1V
05
0*
0)
b100 I
1(
1#
#24
0#
#25
1!
1K
1J
1O
1N
1M
1L
1P
1Q
1R
1S
b101 I
1*
1#
#26
0#
#27
0!
0K
0J
0O
0N
0M
0L
0P
0Q
0R
0S
1T
1U
0*
b110 I
1)
1#
#28
0#
#29
07
1,
0-
10
01
08
0'
0&
1%
1!
1K
1J
0O
1N
0M
1L
15
14
1P
1Q
1R
1S
b111 I
1*
1#
#30
0#
#31
1N
1L
0K
0J
0!
0P
0Q
0R
0S
04
0T
0U
0V
05
0*
0)
b0 I
0(
1#
#32
0#
#33
1P
1Q
1R
1S
b1 I
1*
1#
#34
0#
#35
1!
1N
1L
1K
1J
0P
0Q
0R
0S
1T
1U
0*
b10 I
1)
1#
#36
0#
#37
14
1P
1Q
1R
1S
b11 I
1*
1#
#38
0#
#39
0,
1-
00
11
1'
0!
0N
0L
0K
0J
0P
0Q
0R
0S
04
0T
0U
1V
05
0*
0)
b100 I
1(
1#
#40
0#
#41
1!
1K
1J
1O
1N
1M
1L
1P
1Q
1R
1S
b101 I
1*
1#
#42
0#
#43
0!
0K
0J
0O
0N
0M
0L
0P
0Q
0R
0S
1T
1U
0*
b110 I
1)
1#
#44
0#
#45
1,
0-
10
01
0'
1&
1!
1K
1J
0O
1N
0M
1L
15
14
1P
1Q
1R
1S
b111 I
1*
1#
#46
0#
#47
1N
1L
0K
0J
0!
0P
0Q
0R
0S
04
0T
0U
0V
05
0*
0)
b0 I
0(
1#
#48
0#
#49
1P
1Q
1R
1S
b1 I
1*
1#
#50
0#
#51
1!
1N
1L
1K
1J
0P
0Q
0R
0S
1T
1U
0*
b10 I
1)
1#
#52
0#
#53
14
1P
1Q
1R
1S
b11 I
1*
1#
#54
0#
#55
18
0,
1-
00
11
17
1'
0!
0N
0L
0K
0J
0P
0Q
0R
0S
04
0T
0U
1V
05
0*
0)
b100 I
1(
1#
#56
0#
#57
1!
1K
1J
1O
1N
1M
1L
1P
1Q
1R
1S
b101 I
1*
1#
#58
0#
#59
0!
0K
0J
0O
0N
0M
0L
0P
0Q
0R
0S
1T
1U
0*
b110 I
1)
1#
#60
0#
#61
07
08
1,
0-
10
01
0'
0&
0%
1$
1!
1K
1J
0O
1N
0M
1L
15
14
1P
1Q
1R
1S
b111 I
1*
1#
#62
0#
#63
1N
1L
0K
0J
0!
0P
0Q
0R
0S
04
0T
0U
0V
05
0*
0)
b0 I
0(
1#
#64
0#
#65
1P
1Q
1R
1S
b1 I
1*
1#
#66
0#
#67
1!
1N
1L
1K
1J
0P
0Q
0R
0S
1T
1U
0*
b10 I
1)
1#
#68
0#
#69
14
1P
1Q
1R
1S
b11 I
1*
1#
#70
0#
#71
0,
1-
00
11
1'
0!
0N
0L
0K
0J
0P
0Q
0R
0S
04
0T
0U
1V
05
0*
0)
b100 I
1(
1#
#72
0#
#73
1!
1K
1J
1O
1N
1M
1L
1P
1Q
1R
1S
b101 I
1*
1#
#74
0#
#75
0!
0K
0J
0O
0N
0M
0L
0P
0Q
0R
0S
1T
1U
0*
b110 I
1)
1#
#76
0#
#77
1,
0-
10
01
0'
1&
1!
1K
1J
0O
1N
0M
1L
15
14
1P
1Q
1R
1S
b111 I
1*
1#
#78
0#
#79
1N
1L
0K
0J
0!
0P
0Q
0R
0S
04
0T
0U
0V
05
0*
0)
b0 I
0(
1#
#80
0#
#81
1P
1Q
1R
1S
b1 I
1*
1#
#82
0#
#83
1!
1N
1L
1K
1J
0P
0Q
0R
0S
1T
1U
0*
b10 I
1)
1#
#84
0#
#85
14
1P
1Q
1R
1S
b11 I
1*
1#
#86
0#
#87
0,
1-
00
11
17
1'
0!
0N
0L
0K
0J
0P
0Q
0R
0S
04
0T
0U
1V
05
0*
0)
b100 I
1(
1#
#88
0#
#89
1!
1K
1J
1O
1N
1M
1L
1P
1Q
1R
1S
b101 I
1*
1#
#90
0#
#91
0!
0K
0J
0O
0N
0M
0L
0P
0Q
0R
0S
1T
1U
0*
b110 I
1)
1#
#92
0#
#93
07
1,
0-
10
01
08
0'
0&
1%
1!
1K
1J
0O
1N
0M
1L
15
14
1P
1Q
1R
1S
b111 I
1*
1#
#94
0#
#95
1N
1L
0K
0J
0!
0P
0Q
0R
0S
04
0T
0U
0V
05
0*
0)
b0 I
0(
1#
#96
0#
#97
1P
1Q
1R
1S
b1 I
1*
1#
#98
0#
#99
1!
1N
1L
1K
1J
0P
0Q
0R
0S
1T
1U
0*
b10 I
1)
1#
#100
0#
#101
14
1P
1Q
1R
1S
b11 I
1*
1#
