2020/2020B3A70785P.v
module RSFF(Q, Qbar, S, R, clk, reset);
    output reg Q, Qbar;
    input S, R, clk, reset;

    always @(posedge clk or negedge reset) begin
        if(!reset) begin
            Q <= 1'b1;
            Qbar <= 1'b0;
        end
        else begin
            if(S == 0 && R == 1) begin
                Q <= 1'b0;
                Qbar <= 1'b1;
            end
            else if(S == 1 && R == 0) begin
                Q <= 1'b1;
                Qbar <= 1'b0;
            end
            if(S == 1 && R == 1) begin
                Q <= 1'b1;
                Qbar <= 1'b0;
            end
        end
    end
endmodule

module DFF(Q, Qbar, D, clk, reset);
    output Q, Qbar;
    input D, clk, reset;
    RSFF s(Q, Qbar, D, ~D, clk, reset);
endmodule

module Ripple_Counter(Q, clk, reset);
    output [3:0] Q;
    input clk, reset;
    wire [3:0] Qbar;
    DFF d0(Q[0], Qbar[0], Qbar[0], clk, reset);
    DFF d1(Q[1], Qbar[1], Qbar[1], Qbar[0], reset);
    DFF d2(Q[2], Qbar[2], Qbar[2], Qbar[1], reset);
    DFF d3(Q[3], Qbar[3], Qbar[3], Qbar[2], reset);
endmodule

module MEM1(memout, addr);
    output [7:0] memout;
    input [2:0] addr;
    reg [7:0] mem[0:7];
    assign memout = mem[addr];

    initial begin
        mem[0] = 8'b0001_1111;
        mem[1] = 8'b0011_0001;
        mem[2] = 8'b0101_0011;
        mem[3] = 8'b0111_0101;
        mem[4] = 8'b1001_0111;
        mem[5] = 8'b1011_1001;
        mem[6] = 8'b1101_1011;
        mem[7] = 8'b1111_1101;
    end
endmodule

module MEM2(memout, addr);
    output [7:0] memout;
    input [2:0] addr;
    reg [7:0] mem[0:7];
    assign memout = mem[addr];

    initial begin
        mem[0] = 8'b0000_0000;
        mem[1] = 8'b0010_0010;
        mem[2] = 8'b0100_0100;
        mem[3] = 8'b0110_0110;
        mem[4] = 8'b1000_1000;
        mem[5] = 8'b1010_1010;
        mem[6] = 8'b1100_1100;
        mem[7] = 8'b1110_1110;
    end
endmodule

module MUX2To1(out, in, sel);
    output out;
    input [1:0] in;
    input sel;
    assign out = in[sel];
endmodule

module MUX16To8(out, in, sel);
    output [7:0] out;
    input [15:0] in;
    input sel;
    genvar i;
    parameter n = 8;
    generate
        for(i = 0; i < n; i = i + 1)
            MUX2To1 m(out[i], {in[i+n], in[i]}, sel);
    endgenerate
endmodule

module Fetch_data(data, parity, in);
    output [7:0] data;
    output parity;
    input [3:0] in;
    wire [7:0] memout1, memout2;

    MEM1 m1(memout1, in[2:0]);
    MEM2 m2(memout2, in[2:0]);
    MUX16To8 mx1(data, {memout2, memout1}, in[3]);
    MUX2To1 mx2(parity, {1'b0, 1'b1}, in[3]);
endmodule

module Parity_Checker(match, data, parity);
    output match;
    input [7:0] data;
    input parity;
    assign detectedParity = (data[0] ^ data[1] ^ data[2] ^ data[3] ^ data[4] ^ data[5] ^ data[6] ^ data[7]);
    assign match = (detectedParity == parity);
endmodule

module Design(match, clk, reset);
    output match;
    input clk, reset;
    wire [3:0] q;
    wire [7:0] data;
    wire parity;

    Ripple_Counter r(q, clk, reset);
    Fetch_data f(data, parity, q);
    Parity_Checker p(match, data, parity);
endmodule

module TestBench;
    reg clk, reset;
    wire match;
    Design d(match, clk, reset);

    initial begin
        $dumpfile("f.vcd");
        $dumpvars;
    end

    initial begin
        clk = 1'b0;
        repeat(1000)
            #1 clk = ~clk;
    end

    initial begin
        $monitor($time, " reset=%b, match=%b", reset, match);
        reset = 1'b0;
        #1 reset = 1'b1;
        #100 $finish;
    end
endmodule

2020/f.vcd
$date
	Mon Nov 20 00:02:59 2023
$end
$version
	Icarus Verilog
$end
$timescale
	1s
$end
$scope module TestBench $end
$var wire 1 ! match $end
$var reg 1 " clk $end
$var reg 1 # reset $end
$scope module d $end
$var wire 1 " clk $end
$var wire 1 # reset $end
$var wire 4 $ q [3:0] $end
$var wire 1 % parity $end
$var wire 1 ! match $end
$var wire 8 & data [7:0] $end
$scope module f $end
$var wire 1 % parity $end
$var wire 8 ' memout2 [7:0] $end
$var wire 8 ( memout1 [7:0] $end
$var wire 4 ) in [3:0] $end
$var wire 8 * data [7:0] $end
$scope module m1 $end
$var wire 3 + addr [2:0] $end
$var wire 8 , memout [7:0] $end
$upscope $end
$scope module m2 $end
$var wire 3 - addr [2:0] $end
$var wire 8 . memout [7:0] $end
$upscope $end
$scope module mx1 $end
$var wire 16 / in [15:0] $end
$var wire 1 0 sel $end
$var wire 8 1 out [7:0] $end
$var parameter 32 2 n $end
$scope begin genblk1[0] $end
$var parameter 2 3 i $end
$scope module m $end
$var wire 2 4 in [1:0] $end
$var wire 1 0 sel $end
$var wire 1 5 out $end
$upscope $end
$upscope $end
$scope begin genblk1[1] $end
$var parameter 2 6 i $end
$scope module m $end
$var wire 2 7 in [1:0] $end
$var wire 1 0 sel $end
$var wire 1 8 out $end
$upscope $end
$upscope $end
$scope begin genblk1[2] $end
$var parameter 3 9 i $end
$scope module m $end
$var wire 2 : in [1:0] $end
$var wire 1 0 sel $end
$var wire 1 ; out $end
$upscope $end
$upscope $end
$scope begin genblk1[3] $end
$var parameter 3 < i $end
$scope module m $end
$var wire 2 = in [1:0] $end
$var wire 1 0 sel $end
$var wire 1 > out $end
$upscope $end
$upscope $end
$scope begin genblk1[4] $end
$var parameter 4 ? i $end
$scope module m $end
$var wire 2 @ in [1:0] $end
$var wire 1 0 sel $end
$var wire 1 A out $end
$upscope $end
$upscope $end
$scope begin genblk1[5] $end
$var parameter 4 B i $end
$scope module m $end
$var wire 2 C in [1:0] $end
$var wire 1 0 sel $end
$var wire 1 D out $end
$upscope $end
$upscope $end
$scope begin genblk1[6] $end
$var parameter 4 E i $end
$scope module m $end
$var wire 2 F in [1:0] $end
$var wire 1 0 sel $end
$var wire 1 G out $end
$upscope $end
$upscope $end
$scope begin genblk1[7] $end
$var parameter 4 H i $end
$scope module m $end
$var wire 2 I in [1:0] $end
$var wire 1 0 sel $end
$var wire 1 J out $end
$upscope $end
$upscope $end
$upscope $end
$scope module mx2 $end
$var wire 2 K in [1:0] $end
$var wire 1 L sel $end
$var wire 1 % out $end
$upscope $end
$upscope $end
$scope module p $end
$var wire 8 M data [7:0] $end
$var wire 1 N detectedParity $end
$var wire 1 ! match $end
$var wire 1 % parity $end
$upscope $end
$scope module r $end
$var wire 1 " clk $end
$var wire 1 # reset $end
$var wire 4 O Qbar [3:0] $end
$var wire 4 P Q [3:0] $end
$scope module d0 $end
$var wire 1 Q D $end
$var wire 1 " clk $end
$var wire 1 # reset $end
$var wire 1 R Qbar $end
$var wire 1 S Q $end
$scope module s $end
$var wire 1 T R $end
$var wire 1 Q S $end
$var wire 1 " clk $end
$var wire 1 # reset $end
$var reg 1 S Q $end
$var reg 1 R Qbar $end
$upscope $end
$upscope $end
$scope module d1 $end
$var wire 1 U D $end
$var wire 1 V clk $end
$var wire 1 # reset $end
$var wire 1 W Qbar $end
$var wire 1 X Q $end
$scope module s $end
$var wire 1 Y R $end
$var wire 1 U S $end
$var wire 1 V clk $end
$var wire 1 # reset $end
$var reg 1 X Q $end
$var reg 1 W Qbar $end
$upscope $end
$upscope $end
$scope module d2 $end
$var wire 1 Z D $end
$var wire 1 [ clk $end
$var wire 1 # reset $end
$var wire 1 \ Qbar $end
$var wire 1 ] Q $end
$scope module s $end
$var wire 1 ^ R $end
$var wire 1 Z S $end
$var wire 1 [ clk $end
$var wire 1 # reset $end
$var reg 1 ] Q $end
$var reg 1 \ Qbar $end
$upscope $end
$upscope $end
$scope module d3 $end
$var wire 1 _ D $end
$var wire 1 ` clk $end
$var wire 1 # reset $end
$var wire 1 a Qbar $end
$var wire 1 b Q $end
$scope module s $end
$var wire 1 c R $end
$var wire 1 _ S $end
$var wire 1 ` clk $end
$var wire 1 # reset $end
$var reg 1 b Q $end
$var reg 1 a Qbar $end
$upscope $end
$upscope $end
$upscope $end
$upscope $end
$upscope $end
$enddefinitions $end
$comment Show the parameter values. $end
$dumpall
b111 H
b110 E
b101 B
b100 ?
b11 <
b10 9
b1 6
b0 3
b1000 2
$end
#0
$dumpvars
1c
1b
0a
0`
0_
1^
1]
0\
0[
0Z
1Y
1X
0W
0V
0U
1T
1S
0R
0Q
b1111 P
b0 O
0N
b11101110 M
1L
b1 K
1J
b11 I
1G
b11 F
1D
b11 C
0A
b1 @
1>
b11 =
1;
b11 :
18
b10 7
05
b1 4
b11101110 1
10
b1110111011111101 /
b11101110 .
b111 -
b11111101 ,
b111 +
b11101110 *
b1111 )
b11111101 (
b11101110 '
b11101110 &
0%
b1111 $
0#
0"
1!
$end
#1
0c
1_
1%
0L
15
1A
00
1a
0b
0^
1>
0J
b0 I
1`
1Z
1\
0]
0Y
1;
0G
b1 =
b0 F
1[
1U
1W
0X
1!
1N
0T
18
b11111 &
b11111 *
b11111 1
b11111 M
0D
b1 7
b1 :
b0 C
1V
1Q
b0 '
b0 .
b0 -
b11111 /
b11111 (
b11111 ,
b0 +
b1111 O
1R
b0 $
b0 )
b0 P
0S
1#
1"
#2
0"
#3
1!
1N
1T
08
b10 7
0;
b0 :
0>
b0 =
b110001 &
b110001 *
b110001 1
b110001 M
1D
b11 C
0V
0Q
b100010 '
b100010 .
b1 -
b10001000110001 /
b110001 (
b110001 ,
b1 +
b1110 O
0R
b1 $
b1 )
b1 P
1S
1"
#4
0"
#5
1Y
1G
b11 F
0[
0U
0W
1X
0!
0N
0T
18
b1 7
0;
b10 :
0>
b0 =
b1010011 &
b1010011 *
b1010011 1
b1010011 M
0D
b0 C
1V
1Q
b1000100 '
b1000100 .
b10 -
b100010001010011 /
b1010011 (
b1010011 ,
b10 +
b1101 O
1R
b10 $
b10 )
b10 P
0S
1"
#6
0"
#7
1!
1N
1T
08
b10 7
1;
b11 :
b1110101 &
b1110101 *
b1110101 1
b1110101 M
1D
b11 C
0V
0Q
b1100110 '
b1100110 .
b11 -
b110011001110101 /
b1110101 (
b1110101 ,
b11 +
b1100 O
0R
b11 $
b11 )
b11 P
1S
1"
#8
0"
#9
1^
1J
b11 I
0`
0Z
0\
1]
0Y
0>
b10 =
0G
b0 F
1[
1U
1W
0X
1!
1N
0T
18
b1 7
1;
b1 :
b10010111 &
b10010111 *
b10010111 1
b10010111 M
0D
b0 C
1V
1Q
b10001000 '
b10001000 .
b100 -
b1000100010010111 /
b10010111 (
b10010111 ,
b100 +
b1011 O
1R
b100 $
b100 )
b100 P
0S
1"
#10
0"
#11
1!
1N
1T
08
b10 7
0;
b0 :
1>
b11 =
b10111001 &
b10111001 *
b10111001 1
b10111001 M
1D
b11 C
0V
0Q
b10101010 '
b10101010 .
b101 -
b1010101010111001 /
b10111001 (
b10111001 ,
b101 +
b1010 O
0R
b101 $
b101 )
b101 P
1S
1"
#12
0"
#13
1Y
1G
b11 F
0[
0U
0W
1X
0!
0N
0T
18
b1 7
0;
b10 :
1>
b11 =
b11011011 &
b11011011 *
b11011011 1
b11011011 M
0D
b0 C
1V
1Q
b11001100 '
b11001100 .
b110 -
b1100110011011011 /
b11011011 (
b11011011 ,
b110 +
b1001 O
1R
b110 $
b110 )
b110 P
0S
1"
#14
0"
#15
1!
1N
1T
08
b10 7
1;
b11 :
b11111101 &
b11111101 *
b11111101 1
b11111101 M
1D
b11 C
0V
0Q
b11101110 '
b11101110 .
b111 -
b1110111011111101 /
b11111101 (
b11111101 ,
b111 +
b1000 O
0R
b111 $
b111 )
b111 P
1S
1"
#16
0"
#17
1c
0_
0%
1L
05
0A
10
0a
1b
0^
0J
b0 I
1`
1Z
1\
0]
0Y
0>
b1 =
0G
b0 F
1[
1U
1W
0X
1!
0N
0T
08
b1 7
0;
b1 :
b0 &
b0 *
b0 1
b0 M
0D
b0 C
1V
1Q
b0 '
b0 .
b0 -
b11111 /
b11111 (
b11111 ,
b0 +
b111 O
1R
b1000 $
b1000 )
b1000 P
0S
1"
#18
0"
#19
1!
0N
1T
18
b100010 &
b100010 *
b100010 1
b100010 M
1D
b10 7
b0 :
b0 =
b11 C
0V
0Q
b100010 '
b100010 .
b1 -
b10001000110001 /
b110001 (
b110001 ,
b1 +
b110 O
0R
b1001 $
b1001 )
b1001 P
1S
1"
#20
0"
#21
1Y
1;
1G
b11 F
0[
0U
0W
1X
1!
0N
0T
08
b1000100 &
b1000100 *
b1000100 1
b1000100 M
0D
b1 7
b10 :
b0 =
b0 C
1V
1Q
b1000100 '
b1000100 .
b10 -
b100010001010011 /
b1010011 (
b1010011 ,
b10 +
b101 O
1R
b1010 $
b1010 )
b1010 P
0S
1"
#22
0"
#23
1!
0N
1T
18
b1100110 &
b1100110 *
b1100110 1
b1100110 M
1D
b10 7
b11 :
b11 C
0V
0Q
b1100110 '
b1100110 .
b11 -
b110011001110101 /
b1110101 (
b1110101 ,
b11 +
b100 O
0R
b1011 $
b1011 )
b1011 P
1S
1"
#24
0"
#25
1^
1>
1J
b11 I
0`
0Z
0\
1]
0Y
0;
0G
b10 =
b0 F
1[
1U
1W
0X
1!
0N
0T
08
b10001000 &
b10001000 *
b10001000 1
b10001000 M
0D
b1 7
b1 :
b0 C
1V
1Q
b10001000 '
b10001000 .
b100 -
b1000100010010111 /
b10010111 (
b10010111 ,
b100 +
b11 O
1R
b1100 $
b1100 )
b1100 P
0S
1"
#26
0"
#27
1!
0N
1T
18
b10101010 &
b10101010 *
b10101010 1
b10101010 M
1D
b10 7
b0 :
b11 =
b11 C
0V
0Q
b10101010 '
b10101010 .
b101 -
b1010101010111001 /
b10111001 (
b10111001 ,
b101 +
b10 O
0R
b1101 $
b1101 )
b1101 P
1S
1"
#28
0"
#29
1Y
1;
1G
b11 F
0[
0U
0W
1X
1!
0N
0T
08
b11001100 &
b11001100 *
b11001100 1
b11001100 M
0D
b1 7
b10 :
b11 =
b0 C
1V
1Q
b11001100 '
b11001100 .
b110 -
b1100110011011011 /
b11011011 (
b11011011 ,
b110 +
b1 O
1R
b1110 $
b1110 )
b1110 P
0S
1"
#30
0"
#31
1!
0N
1T
18
b11101110 &
b11101110 *
b11101110 1
b11101110 M
1D
b10 7
b11 :
b11 C
0V
0Q
b11101110 '
b11101110 .
b111 -
b1110111011111101 /
b11111101 (
b11111101 ,
b111 +
b0 O
0R
b1111 $
b1111 )
b1111 P
1S
1"
#32
0"
#33
0c
1_
1%
0L
15
1A
00
1a
0b
0^
1>
0J
b0 I
1`
1Z
1\
0]
0Y
1;
0G
b1 =
b0 F
1[
1U
1W
0X
1!
1N
0T
18
b11111 &
b11111 *
b11111 1
b11111 M
0D
b1 7
b1 :
b0 C
1V
1Q
b0 '
b0 .
b0 -
b11111 /
b11111 (
b11111 ,
b0 +
b1111 O
1R
b0 $
b0 )
b0 P
0S
1"
#34
0"
#35
1!
1N
1T
08
b10 7
0;
b0 :
0>
b0 =
b110001 &
b110001 *
b110001 1
b110001 M
1D
b11 C
0V
0Q
b100010 '
b100010 .
b1 -
b10001000110001 /
b110001 (
b110001 ,
b1 +
b1110 O
0R
b1 $
b1 )
b1 P
1S
1"
#36
0"
#37
1Y
1G
b11 F
0[
0U
0W
1X
0!
0N
0T
18
b1 7
0;
b10 :
0>
b0 =
b1010011 &
b1010011 *
b1010011 1
b1010011 M
0D
b0 C
1V
1Q
b1000100 '
b1000100 .
b10 -
b100010001010011 /
b1010011 (
b1010011 ,
b10 +
b1101 O
1R
b10 $
b10 )
b10 P
0S
1"
#38
0"
#39
1!
1N
1T
08
b10 7
1;
b11 :
b1110101 &
b1110101 *
b1110101 1
b1110101 M
1D
b11 C
0V
0Q
b1100110 '
b1100110 .
b11 -
b110011001110101 /
b1110101 (
b1110101 ,
b11 +
b1100 O
0R
b11 $
b11 )
b11 P
1S
1"
#40
0"
#41
1^
1J
b11 I
0`
0Z
0\
1]
0Y
0>
b10 =
0G
b0 F
1[
1U
1W
0X
1!
1N
0T
18
b1 7
1;
b1 :
b10010111 &
b10010111 *
b10010111 1
b10010111 M
0D
b0 C
1V
1Q
b10001000 '
b10001000 .
b100 -
b1000100010010111 /
b10010111 (
b10010111 ,
b100 +
b1011 O
1R
b100 $
b100 )
b100 P
0S
1"
#42
0"
#43
1!
1N
1T
08
b10 7
0;
b0 :
1>
b11 =
b10111001 &
b10111001 *
b10111001 1
b10111001 M
1D
b11 C
0V
0Q
b10101010 '
b10101010 .
b101 -
b1010101010111001 /
b10111001 (
b10111001 ,
b101 +
b1010 O
0R
b101 $
b101 )
b101 P
1S
1"
#44
0"
#45
1Y
1G
b11 F
0[
0U
0W
1X
0!
0N
0T
18
b1 7
0;
b10 :
1>
b11 =
b11011011 &
b11011011 *
b11011011 1
b11011011 M
0D
b0 C
1V
1Q
b11001100 '
b11001100 .
b110 -
b1100110011011011 /
b11011011 (
b11011011 ,
b110 +
b1001 O
1R
b110 $
b110 )
b110 P
0S
1"
#46
0"
#47
1!
1N
1T
08
b10 7
1;
b11 :
b11111101 &
b11111101 *
b11111101 1
b11111101 M
1D
b11 C
0V
0Q
b11101110 '
b11101110 .
b111 -
b1110111011111101 /
b11111101 (
b11111101 ,
b111 +
b1000 O
0R
b111 $
b111 )
b111 P
1S
1"
#48
0"
#49
1c
0_
0%
1L
05
0A
10
0a
1b
0^
0J
b0 I
1`
1Z
1\
0]
0Y
0>
b1 =
0G
b0 F
1[
1U
1W
0X
1!
0N
0T
08
b1 7
0;
b1 :
b0 &
b0 *
b0 1
b0 M
0D
b0 C
1V
1Q
b0 '
b0 .
b0 -
b11111 /
b11111 (
b11111 ,
b0 +
b111 O
1R
b1000 $
b1000 )
b1000 P
0S
1"
#50
0"
#51
1!
0N
1T
18
b100010 &
b100010 *
b100010 1
b100010 M
1D
b10 7
b0 :
b0 =
b11 C
0V
0Q
b100010 '
b100010 .
b1 -
b10001000110001 /
b110001 (
b110001 ,
b1 +
b110 O
0R
b1001 $
b1001 )
b1001 P
1S
1"
#52
0"
#53
1Y
1;
1G
b11 F
0[
0U
0W
1X
1!
0N
0T
08
b1000100 &
b1000100 *
b1000100 1
b1000100 M
0D
b1 7
b10 :
b0 =
b0 C
1V
1Q
b1000100 '
b1000100 .
b10 -
b100010001010011 /
b1010011 (
b1010011 ,
b10 +
b101 O
1R
b1010 $
b1010 )
b1010 P
0S
1"
#54
0"
#55
1!
0N
1T
18
b1100110 &
b1100110 *
b1100110 1
b1100110 M
1D
b10 7
b11 :
b11 C
0V
0Q
b1100110 '
b1100110 .
b11 -
b110011001110101 /
b1110101 (
b1110101 ,
b11 +
b100 O
0R
b1011 $
b1011 )
b1011 P
1S
1"
#56
0"
#57
1^
1>
1J
b11 I
0`
0Z
0\
1]
0Y
0;
0G
b10 =
b0 F
1[
1U
1W
0X
1!
0N
0T
08
b10001000 &
b10001000 *
b10001000 1
b10001000 M
0D
b1 7
b1 :
b0 C
1V
1Q
b10001000 '
b10001000 .
b100 -
b1000100010010111 /
b10010111 (
b10010111 ,
b100 +
b11 O
1R
b1100 $
b1100 )
b1100 P
0S
1"
#58
0"
#59
1!
0N
1T
18
b10101010 &
b10101010 *
b10101010 1
b10101010 M
1D
b10 7
b0 :
b11 =
b11 C
0V
0Q
b10101010 '
b10101010 .
b101 -
b1010101010111001 /
b10111001 (
b10111001 ,
b101 +
b10 O
0R
b1101 $
b1101 )
b1101 P
1S
1"
#60
0"
#61
1Y
1;
1G
b11 F
0[
0U
0W
1X
1!
0N
0T
08
b11001100 &
b11001100 *
b11001100 1
b11001100 M
0D
b1 7
b10 :
b11 =
b0 C
1V
1Q
b11001100 '
b11001100 .
b110 -
b1100110011011011 /
b11011011 (
b11011011 ,
b110 +
b1 O
1R
b1110 $
b1110 )
b1110 P
0S
1"
#62
0"
#63
1!
0N
1T
18
b11101110 &
b11101110 *
b11101110 1
b11101110 M
1D
b10 7
b11 :
b11 C
0V
0Q
b11101110 '
b11101110 .
b111 -
b1110111011111101 /
b11111101 (
b11111101 ,
b111 +
b0 O
0R
b1111 $
b1111 )
b1111 P
1S
1"
#64
0"
#65
0c
1_
1%
0L
15
1A
00
1a
0b
0^
1>
0J
b0 I
1`
1Z
1\
0]
0Y
1;
0G
b1 =
b0 F
1[
1U
1W
0X
1!
1N
0T
18
b11111 &
b11111 *
b11111 1
b11111 M
0D
b1 7
b1 :
b0 C
1V
1Q
b0 '
b0 .
b0 -
b11111 /
b11111 (
b11111 ,
b0 +
b1111 O
1R
b0 $
b0 )
b0 P
0S
1"
#66
0"
#67
1!
1N
1T
08
b10 7
0;
b0 :
0>
b0 =
b110001 &
b110001 *
b110001 1
b110001 M
1D
b11 C
0V
0Q
b100010 '
b100010 .
b1 -
b10001000110001 /
b110001 (
b110001 ,
b1 +
b1110 O
0R
b1 $
b1 )
b1 P
1S
1"
#68
0"
#69
1Y
1G
b11 F
0[
0U
0W
1X
0!
0N
0T
18
b1 7
0;
b10 :
0>
b0 =
b1010011 &
b1010011 *
b1010011 1
b1010011 M
0D
b0 C
1V
1Q
b1000100 '
b1000100 .
b10 -
b100010001010011 /
b1010011 (
b1010011 ,
b10 +
b1101 O
1R
b10 $
b10 )
b10 P
0S
1"
#70
0"
#71
1!
1N
1T
08
b10 7
1;
b11 :
b1110101 &
b1110101 *
b1110101 1
b1110101 M
1D
b11 C
0V
0Q
b1100110 '
b1100110 .
b11 -
b110011001110101 /
b1110101 (
b1110101 ,
b11 +
b1100 O
0R
b11 $
b11 )
b11 P
1S
1"
#72
0"
#73
1^
1J
b11 I
0`
0Z
0\
1]
0Y
0>
b10 =
0G
b0 F
1[
1U
1W
0X
1!
1N
0T
18
b1 7
1;
b1 :
b10010111 &
b10010111 *
b10010111 1
b10010111 M
0D
b0 C
1V
1Q
b10001000 '
b10001000 .
b100 -
b1000100010010111 /
b10010111 (
b10010111 ,
b100 +
b1011 O
1R
b100 $
b100 )
b100 P
0S
1"
#74
0"
#75
1!
1N
1T
08
b10 7
0;
b0 :
1>
b11 =
b10111001 &
b10111001 *
b10111001 1
b10111001 M
1D
b11 C
0V
0Q
b10101010 '
b10101010 .
b101 -
b1010101010111001 /
b10111001 (
b10111001 ,
b101 +
b1010 O
0R
b101 $
b101 )
b101 P
1S
1"
#76
0"
#77
1Y
1G
b11 F
0[
0U
0W
1X
0!
0N
0T
18
b1 7
0;
b10 :
1>
b11 =
b11011011 &
b11011011 *
b11011011 1
b11011011 M
0D
b0 C
1V
1Q
b11001100 '
b11001100 .
b110 -
b1100110011011011 /
b11011011 (
b11011011 ,
b110 +
b1001 O
1R
b110 $
b110 )
b110 P
0S
1"
#78
0"
#79
1!
1N
1T
08
b10 7
1;
b11 :
b11111101 &
b11111101 *
b11111101 1
b11111101 M
1D
b11 C
0V
0Q
b11101110 '
b11101110 .
b111 -
b1110111011111101 /
b11111101 (
b11111101 ,
b111 +
b1000 O
0R
b111 $
b111 )
b111 P
1S
1"
#80
0"
#81
1c
0_
0%
1L
05
0A
10
0a
1b
0^
0J
b0 I
1`
1Z
1\
0]
0Y
0>
b1 =
0G
b0 F
1[
1U
1W
0X
1!
0N
0T
08
b1 7
0;
b1 :
b0 &
b0 *
b0 1
b0 M
0D
b0 C
1V
1Q
b0 '
b0 .
b0 -
b11111 /
b11111 (
b11111 ,
b0 +
b111 O
1R
b1000 $
b1000 )
b1000 P
0S
1"
#82
0"
#83
1!
0N
1T
18
b100010 &
b100010 *
b100010 1
b100010 M
1D
b10 7
b0 :
b0 =
b11 C
0V
0Q
b100010 '
b100010 .
b1 -
b10001000110001 /
b110001 (
b110001 ,
b1 +
b110 O
0R
b1001 $
b1001 )
b1001 P
1S
1"
#84
0"
#85
1Y
1;
1G
b11 F
0[
0U
0W
1X
1!
0N
0T
08
b1000100 &
b1000100 *
b1000100 1
b1000100 M
0D
b1 7
b10 :
b0 =
b0 C
1V
1Q
b1000100 '
b1000100 .
b10 -
b100010001010011 /
b1010011 (
b1010011 ,
b10 +
b101 O
1R
b1010 $
b1010 )
b1010 P
0S
1"
#86
0"
#87
1!
0N
1T
18
b1100110 &
b1100110 *
b1100110 1
b1100110 M
1D
b10 7
b11 :
b11 C
0V
0Q
b1100110 '
b1100110 .
b11 -
b110011001110101 /
b1110101 (
b1110101 ,
b11 +
b100 O
0R
b1011 $
b1011 )
b1011 P
1S
1"
#88
0"
#89
1^
1>
1J
b11 I
0`
0Z
0\
1]
0Y
0;
0G
b10 =
b0 F
1[
1U
1W
0X
1!
0N
0T
08
b10001000 &
b10001000 *
b10001000 1
b10001000 M
0D
b1 7
b1 :
b0 C
1V
1Q
b10001000 '
b10001000 .
b100 -
b1000100010010111 /
b10010111 (
b10010111 ,
b100 +
b11 O
1R
b1100 $
b1100 )
b1100 P
0S
1"
#90
0"
#91
1!
0N
1T
18
b10101010 &
b10101010 *
b10101010 1
b10101010 M
1D
b10 7
b0 :
b11 =
b11 C
0V
0Q
b10101010 '
b10101010 .
b101 -
b1010101010111001 /
b10111001 (
b10111001 ,
b101 +
b10 O
0R
b1101 $
b1101 )
b1101 P
1S
1"
#92
0"
#93
1Y
1;
1G
b11 F
0[
0U
0W
1X
1!
0N
0T
08
b11001100 &
b11001100 *
b11001100 1
b11001100 M
0D
b1 7
b10 :
b11 =
b0 C
1V
1Q
b11001100 '
b11001100 .
b110 -
b1100110011011011 /
b11011011 (
b11011011 ,
b110 +
b1 O
1R
b1110 $
b1110 )
b1110 P
0S
1"
#94
0"
#95
1!
0N
1T
18
b11101110 &
b11101110 *
b11101110 1
b11101110 M
1D
b10 7
b11 :
b11 C
0V
0Q
b11101110 '
b11101110 .
b111 -
b1110111011111101 /
b11111101 (
b11111101 ,
b111 +
b0 O
0R
b1111 $
b1111 )
b1111 P
1S
1"
#96
0"
#97
0c
1_
1%
0L
15
1A
00
1a
0b
0^
1>
0J
b0 I
1`
1Z
1\
0]
0Y
1;
0G
b1 =
b0 F
1[
1U
1W
0X
1!
1N
0T
18
b11111 &
b11111 *
b11111 1
b11111 M
0D
b1 7
b1 :
b0 C
1V
1Q
b0 '
b0 .
b0 -
b11111 /
b11111 (
b11111 ,
b0 +
b1111 O
1R
b0 $
b0 )
b0 P
0S
1"
#98
0"
#99
1!
1N
1T
08
b10 7
0;
b0 :
0>
b0 =
b110001 &
b110001 *
b110001 1
b110001 M
1D
b11 C
0V
0Q
b100010 '
b100010 .
b1 -
b10001000110001 /
b110001 (
b110001 ,
b1 +
b1110 O
0R
b1 $
b1 )
b1 P
1S
1"
#100
0"
#101
1Y
1G
b11 F
0[
0U
0W
1X
0!
0N
0T
18
b1 7
0;
b10 :
0>
b0 =
b1010011 &
b1010011 *
b1010011 1
b1010011 M
0D
b0 C
1V
1Q
b1000100 '
b1000100 .
b10 -
b100010001010011 /
b1010011 (
b1010011 ,
b10 +
b1101 O
1R
b10 $
b10 )
b10 P
0S
1"
